magiconfig.py
magiconfig-1.0.1.dist-info/LICENSE
magiconfig-1.0.1.dist-info/METADATA
magiconfig-1.0.1.dist-info/WHEEL
magiconfig-1.0.1.dist-info/top_level.txt
magiconfig-1.0.1.dist-info/RECORD
