Metadata-Version: 2.1
Name: magiconfig
Version: 1.0.1
Summary: An extension of argparse to configure Python with Python
Home-page: https://github.com/kpedro88/magiconfig
Author: Kevin Pedro
Author-email: kpedro88@gmail.com
License: MIT
Keywords: config,configuration,argparse,parameters,magiconfig
Platform: UNKNOWN
Classifier: Programming Language :: Python :: 2
Classifier: Programming Language :: Python :: 2.7
Classifier: Programming Language :: Python :: 3
Classifier: Programming Language :: Python :: 3.6
Classifier: Programming Language :: Python :: 3.7
Classifier: License :: OSI Approved :: MIT License
Classifier: Operating System :: OS Independent
Requires-Python: >=2.7, >=3.6
Requires-Dist: six
